super_init/__init__.py
super_init/decorator.py
super_init-0.1.0.dist-info/LICENSE
super_init-0.1.0.dist-info/METADATA
super_init-0.1.0.dist-info/WHEEL
super_init-0.1.0.dist-info/top_level.txt
super_init-0.1.0.dist-info/RECORD
