Metadata-Version: 2.2
Name: super_init
Version: 0.1.0
Summary: A decorator for flexible inheritance in Python
Home-page: https://github.com/csabhijeet/super-init
Author: Abhijeet Kumar
Author-email: abhijeet151@gmail.com
Classifier: Programming Language :: Python :: 3
Classifier: License :: OSI Approved :: MIT License
Classifier: Operating System :: OS Independent
Requires-Python: >=3.6
License-File: LICENSE
Dynamic: author
Dynamic: author-email
Dynamic: classifier
Dynamic: description
Dynamic: description-content-type
Dynamic: home-page
Dynamic: requires-python
Dynamic: summary
